pyckb/__init__.py
pyckb/bech32.py
pyckb/config.py
pyckb/core.py
pyckb/denomination.py
pyckb/ecdsa.py
pyckb/molecule.py
pyckb/objectdict.py
pyckb/rate.py
pyckb/rpc.py
pyckb/secp256k1.py
pyckb/unittest.py
pyckb/wallet.py
pyckb-1.2.3.dist-info/METADATA
pyckb-1.2.3.dist-info/WHEEL
pyckb-1.2.3.dist-info/licenses/LICENSE
pyckb-1.2.3.dist-info/RECORD
