Metadata-Version: 2.4
Name: pyckb
Version: 1.2.3
Summary: pyckb: nervos ckb library for humans
Project-URL: homepage, https://github.com/mohanson/pyckb
Author-email: Mohanson <mohanson@outlook.com>
License: MIT License
License-File: LICENSE
Requires-Dist: requests
